adder/adder.v
module adder (
    input [31:0] A,
    input [31:0] B,
    input sub,
    output [31:0] Out,
    input D,
    input H,
    input O,
    input Q
);

    wire [31:0] B_Real = sub ? ~B : B;

    wire [4:0] Out0 = A[3:0] + B_Real[3:0] + sub;
    wire[4:0] Out1 = A[7:4] + B_Real[7:4] + ((D | H | O) & Out0[4]) + (Q & sub);
    wire[4:0] Out2 = A[11:8] + B_Real[11:8] + ((D | H) & Out1[4]) + ((Q | O) & sub);
    wire[4:0] Out3 = A[15:12] + B_Real[15:12] + ((D | H | O) & Out2[4]) + (Q & sub);
    wire[4:0] Out4 = A[19:16] + B_Real[19:16] + (D & Out3[4]) + ((H | O | Q) & sub);
    wire[4:0] Out5 = A[23:20] + B_Real[23:20] + ((D | H | O) & Out4[4]) + (Q & sub);
    wire[4:0] Out6 = A[27:24] + B_Real[27:24] + ((D | H) & Out5[4]) + ((Q | O) & sub);
    wire[4:0] Out7 = A[31:28] + B_Real[31:28] + ((D | H | O) & Out6[4]) + (Q & sub);

    assign Out = {
        Out7[3:0],
        Out6[3:0],
        Out5[3:0],
        Out4[3:0],
        Out3[3:0],
        Out2[3:0],
        Out1[3:0],
        Out0[3:0]
    };

endmodule

adder/adder_tb.v
module adder_tb;
    reg [31:0] A, B;
    reg D, H, O, Q, sub;
    output [31:0] Out;


    adder uut (
        .A  (A),
        .B  (B),
        .sub(sub),
        .D  (D),
        .H  (H),
        .O  (O),
        .Q  (Q),
        .Out(Out)
    );

    initial begin
        $dumpfile("adder_wave.vcd");
        $dumpvars(0, adder_tb);

        $monitor(
            "D = %b | H = %b | O = %b | Q = %b | Sub = %b | A = %h | B = %h | Out = %h",
            D, H, O, Q, sub, A, B, Out);

        D   = 1;
        H   = 0;
        O   = 0;
        Q   = 0;

        sub = 0;

        A   = 32'd100;
        B   = 32'd20;

        #10;

        D = 0;
        H = 1;

        A = 32'h00020003;
        B = 32'h00040005;

        #10;

        H = 0;
        O = 1;

        A = 32'h01020304;
        B = 32'h02020202;

        #10;

        O = 0;
        Q = 1;

        A = 32'h11111111;
        B = 32'h22222222;

        #10;

        Q   = 0;
        D   = 1;
        sub = 1;
        A   = 32'd100;
        B   = 32'd20;

        #10;

        D = 0;
        H = 1;
        A = 32'h0008000F;
        B = 32'h00020003;

        #10;

        H = 0;
        O = 1;
        A = 32'h03040506;
        B = 32'h02020202;

        #10;

        O = 0;
        Q = 1;
        A = 32'h33333333;
        B = 32'h22222222;

        #10;

        $finish;
    end
endmodule

adder/adder_wave.vcd
$date
	Mon Jun 22 08:49:42 2026
$end
$version
	Icarus Verilog
$end
$timescale
	1s
$end
$scope module adder_tb $end
$var wire 32 ! Out [31:0] $end
$var reg 32 " A [31:0] $end
$var reg 32 # B [31:0] $end
$var reg 1 $ D $end
$var reg 1 % H $end
$var reg 1 & O $end
$var reg 1 ' Q $end
$var reg 1 ( sub $end
$scope module uut $end
$var wire 32 ) A [31:0] $end
$var wire 32 * B [31:0] $end
$var wire 1 $ D $end
$var wire 1 % H $end
$var wire 1 & O $end
$var wire 1 ' Q $end
$var wire 1 ( sub $end
$var wire 5 + Out7 [4:0] $end
$var wire 5 , Out6 [4:0] $end
$var wire 5 - Out5 [4:0] $end
$var wire 5 . Out4 [4:0] $end
$var wire 5 / Out3 [4:0] $end
$var wire 5 0 Out2 [4:0] $end
$var wire 5 1 Out1 [4:0] $end
$var wire 5 2 Out0 [4:0] $end
$var wire 32 3 Out [31:0] $end
$var wire 32 4 B_Real [31:0] $end
$upscope $end
$upscope $end
$enddefinitions $end
$comment Show the parameter values. $end
$dumpall
$end
#0
$dumpvars
b10100 4
b1111000 3
b1000 2
b111 1
b0 0
b0 /
b0 .
b0 -
b0 ,
b0 +
b10100 *
b1100100 )
0(
0'
0&
0%
1$
b10100 #
b1100100 "
b1111000 !
$end
#10
b1100000000000001000 !
b1100000000000001000 3
b1000000000000000101 4
b1000 2
b0 1
b110 .
b1000000000000000101 #
b1000000000000000101 *
b100000000000000011 "
b100000000000000011 )
1%
0$
#20
b100 .
b11000001000000010100000110 !
b11000001000000010100000110 3
b10000000100000001000000010 4
b110 2
b101 0
b11 ,
b10000000100000001000000010 #
b10000000100000001000000010 *
b1000000100000001100000100 "
b1000000100000001100000100 )
1&
0%
#30
b110011001100110011001100110011 !
b110011001100110011001100110011 3
b100010001000100010001000100010 4
b11 2
b11 1
b11 0
b11 /
b11 .
b11 -
b11 +
b100010001000100010001000100010 #
b100010001000100010001000100010 *
b10001000100010001000100010001 "
b10001000100010001000100010001 )
1'
0&
#40
b10101 1
b10000 0
b10000 /
b10000 .
b10000 -
b10000 ,
b10000 +
b11111111111111111111111111101011 4
b1010000 !
b1010000 3
b10100 #
b10100 *
b1100100 "
b1100100 )
b10000 2
1(
1$
0'
#50
b10000 /
b10000 0
b11111111111111011111111111111100 4
b1100000000000001100 !
b1100000000000001100 3
b11100 2
b10000 1
b10110 .
b100000000000000011 #
b100000000000000011 *
b10000000000000001111 "
b10000000000000001111 )
1%
0$
#60
b11111101111111011111110111111101 4
b1000000100000001100000100 !
b1000000100000001100000100 3
b10100 2
b10011 0
b10010 .
b10001 ,
b10000000100000001000000010 #
b10000000100000001000000010 *
b11000001000000010100000110 "
b11000001000000010100000110 )
1&
0%
#70
b11011101110111011101110111011101 4
b10001000100010001000100010001 !
b10001000100010001000100010001 3
b10001 2
b10001 0
b10001 .
b10001 1
b10001 /
b10001 -
b10001 +
b100010001000100010001000100010 #
b100010001000100010001000100010 *
b110011001100110011001100110011 "
b110011001100110011001100110011 )
1'
0&
