shifter/shifter.v
module shifter (
    input [31:0] in,
    input D,
    input H,
    input O,
    input Q,
    input left,
    output [31:0] out
);

    wire [30:0] left_shift = in[30:0];
    wire [30:0] right_shift = in[31:1];

    wire [31:0] shift_temp = left ? {left_shift, 1'b0} : {1'b0, right_shift};

    assign out[3:0] = {(left | D | H | O) & shift_temp[3], shift_temp[2:0]};

    assign out[7:4] = {
        (left | D | H) & shift_temp[7],
        shift_temp[6:5],
        (!left | D | H | O) & shift_temp[4]
    };

    assign out[11:8] = {
        (left | D | H | O) & shift_temp[11],
        shift_temp[10:9],
        (!left | D | H) & shift_temp[8]
    };

    assign out[15:12] = {
        (left | D) & shift_temp[15],
        shift_temp[14:13],
        (!left | D | H | O) & shift_temp[12]
    };

    assign out[19:16] = {
        (left | D | H | O) & shift_temp[19],
        shift_temp[18:17],
        (!left | D) & shift_temp[16]
    };

    assign out[23:20] = {
        (left | D | H) & shift_temp[23],
        shift_temp[22:21],
        (!left | D | H | O) & shift_temp[20]
    };

    assign out[27:24] = {
        (left | D | H | O) & shift_temp[27],
        shift_temp[26:25],
        (!left | D | H) & shift_temp[24]
    };

    assign out[31:28] = {
        shift_temp[31:29], (!left | D | H | O) & shift_temp[28]
    };

endmodule

shifter/shifter_tb.v
module shifter_tb;

    reg [31:0] in;
    reg D, H, O, Q, left;
    wire [31:0] out;

    shifter uut (
        .in(in),
        .D(D),
        .H(H),
        .O(O),
        .Q(Q),
        .left(left),
        .out(out)
    );

    initial begin
        $dumpfile("shifter_wave.vcd");
        $dumpvars(0, shifter_tb);

        $monitor(
            "Left = %b | D = %b | H = %b | O = %b | Q = %b | In = %b | Out = %b",
            left, D, H, O, Q, in, out);

        left = 1;
        D = 1;
        H = 0;
        O = 0;
        Q = 0;

        in = 32'h12345678;

        #10;

        D  = 0;
        H  = 1;
        in = 32'h80008000;

        #10;

        H  = 0;
        O  = 1;
        in = 32'h80808080;

        #10;

        O  = 0;
        Q  = 1;
        in = 32'h88888888;

        #10;

        left = 0;
        D = 1;
        Q = 0;

        in = 32'h2468ACF0;

        #10;

        D  = 0;
        H  = 1;
        in = 32'h00010001;

        #10;

        H  = 0;
        O  = 1;
        in = 32'h01010101;

        #10;

        O  = 0;
        Q  = 1;
        in = 32'h11111111;

        #10;

        $finish;

    end

endmodule

shifter/shifter_wave.vcd
$date
	Mon Jun 22 15:15:27 2026
$end
$version
	Icarus Verilog
$end
$timescale
	1s
$end
$scope module shifter_tb $end
$var wire 32 ! out [31:0] $end
$var reg 1 " D $end
$var reg 1 # H $end
$var reg 1 $ O $end
$var reg 1 % Q $end
$var reg 32 & in [31:0] $end
$var reg 1 ' left $end
$scope module uut $end
$var wire 1 " D $end
$var wire 1 # H $end
$var wire 1 $ O $end
$var wire 1 % Q $end
$var wire 32 ( in [31:0] $end
$var wire 1 ' left $end
$var wire 32 ) shift_temp [31:0] $end
$var wire 31 * right_shift [30:0] $end
$var wire 32 + out [31:0] $end
$var wire 31 , left_shift [30:0] $end
$upscope $end
$upscope $end
$enddefinitions $end
$comment Show the parameter values. $end
$dumpall
$end
#0
$dumpvars
b10010001101000101011001111000 ,
b100100011010001010110011110000 +
b1001000110100010101100111100 *
b100100011010001010110011110000 )
b10010001101000101011001111000 (
1'
b10010001101000101011001111000 &
0%
0$
0#
1"
b100100011010001010110011110000 !
$end
#10
b0 !
b0 +
b10000000000000000 )
b1000000000000000 ,
b1000000000000000100000000000000 *
b10000000000000001000000000000000 &
b10000000000000001000000000000000 (
1#
0"
#20
b1000000010000000100000000 )
b100000001000000010000000 ,
b1000000010000000100000001000000 *
b10000000100000001000000010000000 &
b10000000100000001000000010000000 (
1$
0#
#30
b10001000100010001000100010000 )
b1000100010001000100010001000 ,
b1000100010001000100010001000100 *
b10001000100010001000100010001000 &
b10001000100010001000100010001000 (
1%
0$
#40
b10010001101000101011001111000 !
b10010001101000101011001111000 +
b100100011010001010110011110000 ,
b10010001101000101011001111000 *
b10010001101000101011001111000 )
b100100011010001010110011110000 &
b100100011010001010110011110000 (
0%
1"
0'
#50
b0 !
b0 +
b1000000000000000 )
b10000000000000001 ,
b1000000000000000 *
b10000000000000001 &
b10000000000000001 (
1#
0"
#60
b100000001000000010000000 )
b1000000010000000100000001 ,
b100000001000000010000000 *
b1000000010000000100000001 &
b1000000010000000100000001 (
1$
0#
#70
b1000100010001000100010001000 )
b10001000100010001000100010001 ,
b1000100010001000100010001000 *
b10001000100010001000100010001 &
b10001000100010001000100010001 (
1%
0$
